{
  "Changes": [
    {
      "Action": "EditData",
      "Target": "Data/GarbageCans",
      "TargetField": ["GarbageCans"],
      "Entries": {
        "LiQingFengCourtyard.43.53": {
          "Items": [
            {
              "Condition": "RANDOM 0.1 @addDailyLuck",
              "RandomItemId": [
                "(0)74"
              ]
            }
          ]
        },
        "MirrorLake.37.36": {
          "Items": [
            {
              "Condition": "RANDOM 0.1 @addDailyLuck",
              "RandomItemId": [
                "(0)213"
              ]
            }
          ]
        },
        "MirrorLake.47.39": {
          "Items": [
            {
              "Condition": "RANDOM 0.1 @addDailyLuck",
              "RandomItemId": [
                "(0)204"
              ]
            }
          ]
        },
        "MirrorLake.67.66": {
          "Items": [
            {
              "Condition": "RANDOM 0.1 @addDailyLuck",
              "RandomItemId": [
                "(0)214"
              ]
            }
          ]
        },
        "MirrorLake.67.34": {
          "Items": [
            {
              "Condition": "RANDOM 0.1 @addDailyLuck",
              "RandomItemId": [
                "(0)829"
              ]
            }
          ]
        },
        "MirrorLake.67.37": {
          "Items": [
            {
              "Condition": "RANDOM 0.1 @addDailyLuck",
              "RandomItemId": [
                "(0)851"
              ]
            }
          ]
        },
        "MirrorLake.77.39": {
          "Items": [
            {
              "Condition": "RANDOM 0.1 @addDailyLuck",
              "RandomItemId": [
                "(0)213"
              ]
            }
          ]
        },
        "MirrorLake.109.39": {
          "Items": [
            {
              "Condition": "RANDOM 0.1 @addDailyLuck",
              "RandomItemId": [
                "(0)725"
              ]
            }
          ]
        },
        "MirrorLake.121.39": {
          "Items": [
            {
              "Condition": "RANDOM 0.1 @addDailyLuck",
              "RandomItemId": [
                "(0)567"
              ]
            }
          ]
        },
        "BazaarWest.77.20": {
          "Items": [
            {
              "Condition": "RANDOM 0.1 @addDailyLuck",
              "RandomItemId": [
                "(0)283"
              ]
            }
          ]
        },
        "BazaarWest.47.20": {
          "Items": [
            {
              "Condition": "RANDOM 0.1 @addDailyLuck",
              "RandomItemId": [
                "(0)426"
              ]
            }
          ]
        },
        "BazaarWest.35.20": {
          "Items": [
            {
              "Condition": "RANDOM 0.1 @addDailyLuck",
              "RandomItemId": [
                "(0)834"
              ]
            }
          ]
        },
        "RedPandaBazaar.15.20": {
          "Items": [
            {
              "Condition": "RANDOM 0.1 @addDailyLuck",
              "RandomItemId": [
                "(0)64"
              ]
            }
          ]
        },
        "RedPandaBazaar.27.28": {
          "Items": [
            {
              "Condition": "RANDOM 0.1 @addDailyLuck",
              "RandomItemId": [
                "(0)393"
              ]
            }
          ]
        },
        "RedPandaBazaar.23.28": {
          "Items": [
            {
              "Condition": "RANDOM 0.1 @addDailyLuck",
              "RandomItemId": [
                "(0)400"
              ]
            }
          ]
        },
        "RedPandaBazaar.28.27": {
          "Items": [
            {
              "Condition": "RANDOM 0.1 @addDailyLuck",
              "RandomItemId": [
                "(0)402"
              ]
            }
          ]
        },
        "RedPandaBazaar.23.29": {
          "Items": [
            {
              "Condition": "RANDOM 0.1 @addDailyLuck",
              "RandomItemId": [
                "(0)720"
              ]
            }
          ]
        },
        "RedPandaBazaar.23.31": {
          "Items": [
            {
              "Condition": "RANDOM 0.1 @addDailyLuck",
              "RandomItemId": [
                "(0)637"
              ]
            }
          ]
        },
        "RedPandaBazaar.27.31": {
          "Items": [
            {
              "Condition": "RANDOM 0.1 @addDailyLuck",
              "RandomItemId": [
                "(0)410"
              ]
            }
          ]
        },
        "RedPandaBazaar.28.31": {
          "Items": [
            {
              "Condition": "RANDOM 0.1 @addDailyLuck",
              "RandomItemId": [
                "(0)306"
              ]
            }
          ]
        },
        "RedPandaBazaar.14.40": {
          "Items": [
            {
              "Condition": "RANDOM 0.1 @addDailyLuck",
              "RandomItemId": [
                "(0)701"
              ]
            }
          ]
        },
        "RedPandaBazaar.14.41": {
          "Items": [
            {
              "Condition": "RANDOM 0.1 @addDailyLuck",
              "RandomItemId": [
                "(0)258"
              ]
            }
          ]
        },
        "RedPandaBazaar.39.41": {
          "Items": [
            {
              "Condition": "RANDOM 0.1 @addDailyLuck",
              "RandomItemId": [
                "(0)296"
              ]
            }
          ]
        },
        "RedPandaBazaar.49.41": {
          "Items": [
            {
              "Condition": "RANDOM 0.1 @addDailyLuck",
              "RandomItemId": [
                "(0)221"
              ]
            }
          ]
        }
      }
    }
  ]
}